foxbox/__init__.py
foxbox/tools.py
FoxBox-0.0.5.dist-info/License.txt .txt
FoxBox-0.0.5.dist-info/METADATA
FoxBox-0.0.5.dist-info/WHEEL
FoxBox-0.0.5.dist-info/top_level.txt
FoxBox-0.0.5.dist-info/RECORD
