Metadata-Version: 2.1
Name: FoxBox
Version: 0.0.5
Summary: An usefull package
Author: Batte
License-File: License.txt .txt
